{
	"name": "Meta Data",
	"properties": {
		"activities": [
			{
				"name": "Get Metadata1",
				"type": "GetMetadata",
				"dependsOn": [],
				"policy": {
					"timeout": "0.12:00:00",
					"retry": 0,
					"retryIntervalInSeconds": 30,
					"secureOutput": false,
					"secureInput": false
				},
				"userProperties": [],
				"typeProperties": {
					"dataset": {
						"referenceName": "People_Data",
						"type": "DatasetReference"
					},
					"fieldList": [
						"size",
						"exists",
						"itemName",
						"lastModified"
					],
					"storeSettings": {
						"type": "AzureBlobFSReadSettings",
						"recursive": true,
						"enablePartitionDiscovery": false
					},
					"formatSettings": {
						"type": "DelimitedTextReadSettings"
					}
				}
			}
		],
		"annotations": [],
		"lastPublishTime": "2023-02-18T14:43:21Z"
	},
	"type": "Microsoft.Synapse/workspaces/pipelines"
}